Metadata-Version: 2.1
Name: marcdata
Version: 1.1.0
Summary: Parse MARC files into simple data structures
Home-page: https://github.com/seanredmond/py-marc-data
Author: Sean Redmond
Author-email: github-smr@sneakemail.com
License: MIT
Platform: UNKNOWN
Classifier: License :: OSI Approved :: MIT License
Classifier: Programming Language :: Python
Requires-Python: >=3.5.0
Provides-Extra: dev
